cfme_testcases/__init__.py
cfme_testcases/cfme_parsereq.py
cfme_testcases/cli.py
cfme_testcases/configuration.py
cfme_testcases/consts.py
cfme_testcases/exceptions.py
cfme_testcases/pytest_collect.py
cfme_testcases/requirements.py
cfme_testcases/submit.py
cfme_testcases/testcases.py
cfme_testcases/testsuites.py
cfme_testcases/utils.py
cfme_testcases/collector/__init__.py
cfme_testcases/collector/filters.py
cfme_testcases/collector/missing.py
cfme_testcases/collector/testcases_svn.py
cfme_testcases/collector/xmls_collector.py
cfme_testcases-0.15.2.dist-info/METADATA
cfme_testcases-0.15.2.dist-info/WHEEL
cfme_testcases-0.15.2.dist-info/entry_points.txt
cfme_testcases-0.15.2.dist-info/top_level.txt
cfme_testcases-0.15.2.dist-info/RECORD
