Metadata-Version: 2.1
Name: cfme-testcases
Version: 0.15.2
Summary: Create new testrun and upload missing testcases using Polarion Importers
Home-page: https://gitlab.com/mkourim/cfme-testcases
Author: Martin Kourim
Author-email: mkourim@redhat.com
License: MIT
Keywords: polarion,testing
Platform: UNKNOWN
Classifier: Development Status :: 3 - Alpha
Classifier: Topic :: Software Development :: Libraries :: Python Modules
Classifier: Topic :: Software Development :: Testing
Classifier: License :: OSI Approved :: MIT License
Classifier: Programming Language :: Python :: 3.5
Classifier: Programming Language :: Python :: 3.6
Classifier: Programming Language :: Python :: 3.7
Classifier: Intended Audience :: Developers
Requires-Dist: dump2polarion (>=0.40.0)
Requires-Dist: python-box
